astoria/__init__.py
astoria/astctl/__init__.py
astoria/astctl/command.py
astoria/astctl/list_disks.py
astoria/astctl/metadata/__init__.py
astoria/astctl/metadata/set.py
astoria/astctl/metadata/show.py
astoria/astctl/static_disks/__init__.py
astoria/astctl/static_disks/add.py
astoria/astctl/static_disks/remove.py
astoria/astctl/static_disks/remove_all.py
astoria/astctl/usercode/__init__.py
astoria/astctl/usercode/kill.py
astoria/astctl/usercode/log.py
astoria/astctl/usercode/restart.py
astoria/astctl/usercode/show.py
astoria/astctl/usercode/trigger.py
astoria/astdiskd/__init__.py
astoria/astdiskd/disk_manager.py
astoria/astdiskd/disk_provider.py
astoria/astdiskd/static.py
astoria/astdiskd/udisks.py
astoria/astmetad/__init__.py
astoria/astmetad/metadata_cache.py
astoria/astmetad/metadata_disk_lifecycle.py
astoria/astmetad/metadata_manager.py
astoria/astprocd/__init__.py
astoria/astprocd/process_manager.py
astoria/astprocd/usercode_lifecycle.py
astoria/astwifid.py
astoria/common/__init__.py
astoria/common/code_status.py
astoria/common/components/__init__.py
astoria/common/components/component.py
astoria/common/components/consumer.py
astoria/common/components/manager.py
astoria/common/config/__init__.py
astoria/common/config/system.py
astoria/common/config/user.py
astoria/common/disks/__init__.py
astoria/common/disks/constraints.py
astoria/common/disks/structs.py
astoria/common/disks/type_calculator.py
astoria/common/ipc/__init__.py
astoria/common/ipc/broadcast_event.py
astoria/common/ipc/manager_messages.py
astoria/common/ipc/manager_requests.py
astoria/common/metadata.py
astoria/common/mixins/__init__.py
astoria/common/mixins/disk_handler.py
astoria/common/mqtt/__init__.py
astoria/common/mqtt/broadcast_helper.py
astoria/common/mqtt/topic.py
astoria/common/mqtt/wrapper.py
astoria/py.typed
astoria-0.11.3.dist-info/LICENSE
astoria-0.11.3.dist-info/METADATA
astoria-0.11.3.dist-info/WHEEL
astoria-0.11.3.dist-info/entry_points.txt
astoria-0.11.3.dist-info/RECORD
